unalix/__init__.py
unalix/__version__.py
unalix/_config.py
unalix/_core.py
unalix/_exceptions.py
unalix/_http.py
unalix/_utils.py
unalix/package_data/body_redirects.json
unalix/package_data/ca-bundle.crt
unalix/package_data/cookies_required.json
unalix/package_data/data.min.json
unalix/package_data/unalix-data.min.json
Crestify_Unalix-0.6.1.dist-info/LICENSE
Crestify_Unalix-0.6.1.dist-info/METADATA
Crestify_Unalix-0.6.1.dist-info/WHEEL
Crestify_Unalix-0.6.1.dist-info/top_level.txt
Crestify_Unalix-0.6.1.dist-info/RECORD
