Metadata-Version: 2.1
Name: Crestify-Unalix
Version: 0.6.1
Summary: A simple module that removes tracking fields from URLs and unshort shortened URLs.
Home-page: https://github.com/crestify/Unalix
Author: crestify
Author-email: asad@crestify.com
License: LGPL-3.0
Platform: UNKNOWN
Classifier: License :: OSI Approved :: GNU Lesser General Public License v3 (LGPLv3)
Classifier: Operating System :: Unix
Classifier: Operating System :: Android
Classifier: Topic :: Internet
Classifier: Topic :: Security
Classifier: Development Status :: 5 - Production/Stable
Classifier: Intended Audience :: Developers
Classifier: Programming Language :: Python :: 3.6
Classifier: Programming Language :: Python :: 3.7
Classifier: Programming Language :: Python :: 3.8
Classifier: Programming Language :: Python :: 3.9
Requires-Python: >=3.6
